{"show_name": "Servant Princess (OAV)", "other_title": ["Elfina - La princesa esclava (Spanish)", "Elufina - Inyoru e to Urareta \u014ckoku de\u2026 The Animation (Japanese)", "Elufina - Servant Princess", "\u30a8\u30eb\u30d5\u30a3\u30fc\u30ca (Japanese)", "\u30a8\u30eb\u30d5\u30a3\u30fc\u30ca\uff5e\u6deb\u591c\u3078\u3068\u58f2\u3089\u308c\u305f\u738b\u56fd\u3067\u2026\uff5e The Animation (Japanese)"], "genre": ["erotica"], "theme": [], "plot": "On the day Princess Erufina of Fiel was to marry Prince Kwan, the Valdland army, led by Prince Viceard Balbacil attacked both Kwan's party and Firan castle. In the resulting Valdland victory, Kwan is seriously injured and Erufina, along with all of the other women of Fiel, are forced into sexual subjugation. Viceard's plans are turned upside down, however, by the arrival of his first-love turned step-mother Marna, who brings Viceard news that his father plans to frame and kill him. With the moderating force of Marna's presence on him, Erufina is exposed to Viceard's softer side, as the king's arrival and Kwan's escape promise to shake the occupied kingdom of Fiel.", "episode": "3", "vintage": ["2003-08-22 to 2004-01-23"], "official_website": "http://www.pinkpineapple.co.jp/title/a/elfina/1/index.html", "opening_theme": [], "ending_theme": [], "insert_song": [], "image": "https://cdn.animenewsnetwork.com/thumbnails/fit200x200/encyc/A3964-26.jpg", "file_category": "e"}