{"show_name": "Eiga Kuma no Gakk\u014d: Patissier Jackie to Ohisama no Sweets (movie)", "other_title": ["\u6620\u753b \u304f\u307e\u306e\u304c\u3063\u3053\u3046 \u30d1\u30c6\u30a3\u30b7\u30a8\u30fb\u30b8\u30e3\u30c3\u30ad\u30fc\u3068\u304a\u3072\u3055\u307e\u306e\u30b9\u30a4\u30fc\u30c4 (Japanese)"], "genre": [], "theme": [], "plot": "", "episode": 0, "vintage": ["2017-08-25"], "official_website": [[]], "opening_theme": [], "ending_theme": ["\"Sayonara da yo, Mister\" by Daisuke Yokoyama feat. Sara Honda"], "insert_song": [], "image": "https://cdn.animenewsnetwork.com/thumbnails/fit200x200/encyc/A23057-1605112330.1583104214.jpg", "file_category": "e"}