{"show_name": "Chocolate Underground (ONA)", "other_title": ["\u30c1\u30e7\u30b3\u30ec\u30fc\u30c8\u30fb\u30a2\u30f3\u30c0\u30fc\u30b0\u30e9\u30a6\u30f3\u30c9 (Japanese)"], "genre": ["adventure"], "theme": ["police"], "plot": "Chocolate is now illegal. The story takes place in present day, the Good for You Party has won the election and announced the amazing Chocolate Prohibition law. They prohibit all sweet things, including chocolates, because they are harmful to ones health. Two boys, Huntley and Smudger, stand up to fight against the law. With help from Louise and other friends, they begin to bootleg chocolate.", "episode": "13", "vintage": ["2008-06-12", "2010-01-29 (Italy - Future Film Festival)"], "official_website": "http://www.choco-bar.jp/", "opening_theme": [], "ending_theme": ["\"Make Up\" by Kana Nishino"], "insert_song": [], "image": "https://cdn.animenewsnetwork.com/thumbnails/fit200x200/encyc/A9599-33.jpg", "file_category": "c"}