{"show_name": "A Certain Scientific Railgun T (TV 3)", "other_title": ["Toaru Kagaku no Railgun T (Japanese)", "A Certain Scientific Railgun", "\u3068\u3042\u308b\u79d1\u5b66\u306e\u8d85\u96fb\u78c1\u7832 Third Season (Japanese)", "\u3068\u3042\u308b\u79d1\u5b66\u306e\u8d85\u96fb\u78c1\u7832T (Japanese)", "\u3068\u3042\u308b\u79d1\u5b66\u306e\u8d85\u96fb\u78c1\u7832\u7b2c3\u671f (Japanese)"], "genre": ["action", "comedy", "drama", "science fiction"], "theme": ["clones", "crime busters", "cyborg", "dreams", "espers", "fanservice", "human experimentation", "mind control", "school", "shoujo-ai", "superpowers"], "plot": "The Daihasei Festival is under way and the prestigious Tokiwadai Middle School, where the Ace of Tokiwadai, Mikoto Misaka reside, is one of the schools participating in this annual sports fest. However, not all are fun and games as people behind the shadows start to plot a new threat that will endanger Mikoto and the whole Academy City. After the Daihasei Festival, Mikoto and her friends find themselves being involved in multiple incidents surrounding special cards that supposedly record people's dreams.", "episode": "25", "vintage": ["2020-01-10"], "official_website": "http://toaru-project.com/railgun_3/", "opening_theme": ["\"final phase\" by fripSide", "\"dual existence\" by fripSide"], "ending_theme": ["\"final phase\" by fripSide (ep 1)", "\"nameless story\" by Kishida Ky\u014ddan & The Akeboshi Rockets", "\"Aoarashi no ato de\" (\u9752\u5d50\u306e\u3042\u3068\u3067) by sajou no hana"], "insert_song": ["\"Koko ni Itai\" (\u3053\u3053\u306b\u3044\u305f\u3044) by sajou no hana (ep 15)"], "image": "https://cdn.animenewsnetwork.com/thumbnails/fit200x200/encyc/A21484-2968424897.1595645128.jpg", "file_category": "c"}