{"show_name": "Requiem from the Darkness (TV)", "other_title": ["Hundred Stories", "Kosetsu Hyaku Monogatari (Japanese)", "Kyogoku Natsuhiko Kosetsu Hyaku Monogatari (Japanese)", "Natsuhiko Kyougoku's Worldly Horror Stories", "Requiem para la oscuridad (Spanish)", "\u0420\u0435\u043a\u0432\u0438\u0435\u043c \u0438\u0437 \u0422\u044c\u043c\u044b (Russian)", "\u4eac\u6975\u590f\u5f66 \u5df7\u8aac\u767e\u7269\u8a9e (Japanese)", "100 stories (Japanese)"], "genre": ["horror", "mystery", "psychological", "supernatural"], "theme": ["folklore", "historical", "mythology"], "plot": "Tired of writing riddles for children, Yamaoka Momosuke plans on gathering spooky and gruesome stories and publishing them in an anthology called Hyakumonogatari (\"One Hundred Tales\"). While researching these old myths and legends he comes across a mysterious trio who call themselves the Ongyou. They are detectives who are investigating the legends to reveal their truths...and bring those in the wrong to justice. Each time Momosuke meets the Ongyou he must face horrible truths and battle with his morals, but he's seeing things he shouldn't be seeing...", "episode": "13", "vintage": ["2003-10-03 to 2003-12-26", "2007-10-20 to 2008-01-12 (G4TechTV Canada - Anime Current)"], "official_website": "http://www.requiemfromdarkness.com/", "opening_theme": ["\"Flame\" by Keiko Lee"], "ending_theme": ["\"The Moment of Love\" by Keiko Lee"], "insert_song": [], "image": "https://cdn.animenewsnetwork.com/thumbnails/crop900x350/video/category/653/key_art_requiem_from_the_darkness.jpg", "file_category": "other"}