{"show_name": "Duel Masters: Hamukatsu to Dogiragon no Curry-pan Dai-b\u014dken (movie)", "other_title": ["\u30c7\u30e5\u30a8\u30eb\u30fb\u30de\u30b9\u30bf\u30fc\u30ba \u30cf\u30e0\u30ab\u30c4\u3068\u30c9\u30ae\u30e9\u30b4\u30f3\u306e\u30ab\u30ec\u30fc\u30d1\u30f3\u5927\u5192\u967a (Japanese)"], "genre": [], "theme": [], "plot": "", "episode": "10 minutes", "vintage": ["2016-03-19"], "official_website": [[]], "opening_theme": [], "ending_theme": [], "insert_song": [], "image": "https://cdn.animenewsnetwork.com/thumbnails/fit200x200/encyc/A18477-2287983850.1465968604.jpg", "file_category": "d"}