{"show_name": "My Hero Academia (TV 4)", "other_title": ["Boku no Hero Academia (Japanese)", "\u50d5\u306e\u30d2\u30fc\u30ed\u30fc\u30a2\u30ab\u30c7\u30df\u30a2 (Japanese)"], "genre": [], "theme": [], "plot": "", "episode": 0, "vintage": ["2019-10-12"], "official_website": "http://heroaca.com/", "opening_theme": ["\"Polaris\" by BLUE ENCOUNT", "\"Starmarker\" by KANA-BOON"], "ending_theme": ["\"Koukai no Uta\" by Sayuri", "\"shout Baby\" by Ryoku Oushoku Shakai"], "insert_song": ["\"Hero too\" by KYOKA JIRO Starring Chrissy Costanza (ep 23)"], "image": "https://cdn.animenewsnetwork.com/thumbnails/fit200x200/encyc/A22265-1852955203.1568050421.jpg", "file_category": "b"}