{"show_name": "UFO Senshi Daiapolon (TV)", "other_title": ["Apolon, rey del espacio (Spanish)", "Daiapolon (Japanese)", "Historia del Diapolon (Spanish)", "UFO Diapolon, guerriero spaziale (Italian)", "UFO Warrior Dai Apolon", "\uff35\uff26\uff2f\u6226\u58eb\u30c0\u30a4\u30a2\u30dd\u30ed\u30f3 (Japanese)"], "genre": ["action", "adventure", "science fiction"], "theme": ["mecha", "super robot"], "plot": "", "episode": "26", "vintage": ["1976-04-06 to 1976-09-28"], "official_website": [[]], "opening_theme": ["\"UFO Senshi Daiapolon\" by Masato Shimon"], "ending_theme": ["\"UFO Shounendan\" by Masato Shimon"], "insert_song": [], "image": "https://cdn.animenewsnetwork.com/thumbnails/fit200x200/encyc/A1291-4203970341.1527926299.jpg", "file_category": "d"}