{"show_name": "Hi-no-youjin (movie)", "other_title": ["Combustible", "\u706b\u8981\u93ae (Japanese)"], "genre": [], "theme": [], "plot": "The events that led to the Great Fire of Meireki which destroyed more than half of the Japanese capital city of Edo.", "episode": "13 minutes", "vintage": ["2012-06-04", "2013-07-20 (with Short Peace compilation)"], "official_website": [[]], "opening_theme": [], "ending_theme": [], "insert_song": [], "image": "https://cdn.animenewsnetwork.com/thumbnails/fit200x200/encyc/A14251-1863310615.1370197124.jpg", "file_category": "c"}