{"show_name": "Immorality (OAV)", "other_title": ["Equation of the Immoral", "In no H\u014dteishiki (Japanese)", "Sexo en el Internado (Spanish)", "Unmoralische Daemonen (German)", "\u6deb\u306e\u65b9\u7a0b\u5f0f (Japanese)"], "genre": ["erotica"], "theme": [], "plot": "Sayako is a new nurse at a certain school. She is what you call a diva: nice pretty face, slender body with the perfect curves and last but not least, very well-formed bust. But there is more to her than meets the eye...", "episode": "2", "vintage": ["2004-03-25 to 2004-11-25"], "official_website": "http://www.milky-anime.com/01/viewer3/index.cgi?action=lineup&mode=milky&dir=houteishiki&file=houteishiki-1", "opening_theme": [], "ending_theme": [], "insert_song": [], "image": "https://cdn.animenewsnetwork.com/thumbnails/fit200x200/encyc/A5731-4.jpg", "file_category": "e"}