{"show_name": "Blue Exorcist: Kyoto Saga (TV)", "other_title": ["Ao no Exorcist: Kyoto Fuj\u014d \u014c-hen (Japanese)", "Blue Exorcist: Kyoto Impure King Arc", "\u9752\u306e\u7953\u9b54\u5e2b \u4eac\u90fd\u4e0d\u6d44\u738b\u7bc7 (Japanese)"], "genre": ["supernatural"], "theme": [], "plot": "Rin Okumura bears the curse of being Satan's illegitimate son. He decides to hide his origins and enrolls at the Exorcism Cram School, a training institute for exorcists located on the True Cross Academy grounds. During an attack by Amaimon, the King of Earth, his identity as the Son of Satan is revealed. His friends are terrified and start to distance themselves. Then someone steals the Left Eye of the Impure King that had been sealed away in the deepest part of the academy. Rin and the others find themselves in an unexpected crisis.", "episode": "12", "vintage": ["2017-01-06"], "official_website": "http://www.ao-ex.com/", "opening_theme": ["\"Itteki no Eiky\u014d\" (\u4e00\u6ef4\u306e\u5f71\u97ff; Drop's Influence) by UVERworld"], "ending_theme": ["\"Kono Te de\" (\u30b3\u30ce\u624b\u30c7; With This Hand) by Rin Akatsuki"], "insert_song": [], "image": "https://cdn.animenewsnetwork.com/thumbnails/fit200x200/encyc/A18528-2642236378.1482024401.jpg", "file_category": "b"}