{"show_name": "Y\u016bsei Kamen (TV)", "other_title": ["Asteroid Mask", "El Enmascarado Espacial (Spanish)", "Planetary Mask", "SUPER-HOMEM DO ESPA\u00c7O (Portuguese)", "\u904a\u661f\u4eee\u9762 (Japanese)"], "genre": ["science fiction"], "theme": [], "plot": "", "episode": "39", "vintage": ["1966-06-03 to 1967-02-21"], "official_website": [[]], "opening_theme": [], "ending_theme": [], "insert_song": [], "image": "https://cdn.animenewsnetwork.com/thumbnails/fit200x200/encyc/A2366-9.jpg", "file_category": "a"}