{"show_name": "City Hunter: Bay City Wars (movie)", "other_title": ["City Hunter Special: Guerra al Bay City Hotel (Italian)", "City Hunter: La ciudad portuaria en guerra (Spanish)", "\u30b7\u30c6\u30a3\u30fc\u30cf\u30f3\u30bf\u30fc \u30d9\u30a4\u30b7\u30c6\u30a3\u30a6\u30a9\u30fc\u30ba (Japanese)"], "genre": ["action", "comedy"], "theme": [], "plot": "A new island resort has been built in Tokyo bay, and it is run by one of the world's most powerful super computers. The City Hunter gang has been invited to the grand opening party, but only Miki & Kaori have gotten there. Soon, they and the rest of the party goers are taken hostage by an exiled South American dictator called General Gillium. Now it's up to Ryo and Umibozu to free the hostages, and prevent Gillium's daughter from using the super computer to launch a nuclear attack on the USA.", "episode": "45 minutes", "vintage": ["1990-08-25", "2006 (Spain)"], "official_website": "http://www.sunrise-inc.co.jp/work/detail.php?cid=233", "opening_theme": [], "ending_theme": ["\"Rock My Love\" by Yoko Oginome"], "insert_song": [], "image": "https://cdn.animenewsnetwork.com/thumbnails/fit200x200/encyc/A549-1859918877.1521669788.jpg", "file_category": "c"}