{"show_name": "It's a Family Affair (OAV)", "other_title": ["Ane to Boin (Japanese)", "\u0421\u0435\u043c\u0435\u0439\u043d\u043e\u0435 \u0434\u0435\u043b\u043e (Russian)", "\u59c9\u3068\u30dc\u30a4\u30f3 (Japanese)"], "genre": ["erotica"], "theme": ["harem", "oppai"], "plot": "In a lonely home without parents of any sort resides Keisuke surrounded by ten step sisters, all of which have the urge to get more intimate with their cute younger brother and they eventually suceed when Keisuke begins to realize their submissiveness.", "episode": "2", "vintage": ["2005-12-25 to 2006-07-25"], "official_website": "http://www.ms-pictures.com/label/milky/products/detail.php?id=198", "opening_theme": [], "ending_theme": [], "insert_song": [], "image": "https://cdn.animenewsnetwork.com/thumbnails/fit200x200/encyc/A6994-15.jpg", "file_category": "a"}