{"show_name": "BBK/BRNK: The Gentle Giants of the Galaxy (TV)", "other_title": ["BBK/BRNK Hoshi no Kyojin (Japanese)", "BUBUKI/BURANKI The Gentle Giants of the Galaxy", "\u30d6\u30d6\u30ad\u30fb\u30d6\u30e9\u30f3\u30ad \u661f\u306e\u5de8\u4eba (Japanese)"], "genre": ["action", "drama", "science fiction"], "theme": [], "plot": "In the world of BBK/BRNK, It's been ten years since Azuma Kazuki has been in Japan, and upon his arrival he is taken prisoner by a group of armed men. Azuma is saved by his childhood friend, Kogane Asabuki, thanks to a living weapon she wields on her right hand, known as a Bubuki. Learning about these weapons, Azuma becomes a Bubuki wielder himself and sets out on a journey.", "episode": "12", "vintage": ["2016-10-01"], "official_website": "http://bbkbrnk.com/", "opening_theme": ["\"Reir\u014d taru Junketsu wa 'K\u014den' no Kairai o Hayarase, Gy\u014dten ni Kirameku Akashi o Kizamu\" by Megumi Han"], "ending_theme": ["\"so beautiful ;- )\" by Mikako Komatsu"], "insert_song": [], "image": "https://cdn.animenewsnetwork.com/thumbnails/fit200x200/encyc/A18682-1022007917.1474968142.jpg", "file_category": "b"}