{"show_name": "Ch\u014d Zenmai Robo Patrush (TV)", "other_title": ["\u8d85\u30bc\u30f3\u30de\u30a4\u30ed\u30dc \u30d1\u30c8\u30e9\u30c3\u30b7\u30e5 (Japanese)"], "genre": ["comedy", "science fiction"], "theme": [], "plot": "", "episode": "1 minutes", "vintage": ["2013-12-07"], "official_website": "http://zenmairobo.com/", "opening_theme": [], "ending_theme": [], "insert_song": [], "image": "https://cdn.animenewsnetwork.com/thumbnails/fit200x200/encyc/A15739-2821921213.1385847093.jpg", "file_category": "c"}