{"show_name": "Doggie March (movie)", "other_title": ["Le Tr\u00e9sor de Loyaux Serviteurs (French)", "Rock el valiente (Spanish)", "Wan Wan Ch\u016bshingura (Japanese)", "\u308f\u3093\u308f\u3093\u5fe0\u81e3\u8535 (Japanese)"], "genre": ["adventure", "comedy", "drama"], "theme": [], "plot": "", "episode": "81 minutes", "vintage": ["1963-12-21"], "official_website": "http://lineup.toei-anim.co.jp/en/movie/movie_wanwan/", "opening_theme": ["\"Wan Wan Chuushingura\" (\u308f\u3093\u308f\u3093\u30de\u30fc\u30c1) by Duke Aces"], "ending_theme": [], "insert_song": [], "image": "https://cdn.animenewsnetwork.com/thumbnails/fit200x200/encyc/A3304-1322784431.1517895138.jpg", "file_category": "d"}