{"show_name": "Bakuman. 3 (TV)", "other_title": ["\u30d0\u30af\u30de\u30f3\u30023 (Japanese)"], "genre": ["drama"], "theme": [], "plot": "Moritaka Mashiro and Akito Takagi have come a long way since they started making manga in middle school, but trials still await them as they head towards their goal of getting an anime adaptation for one of their manga. As they continue to grow as artists and as people, they will be faced with new friends, new rivals, and new hurdles to overcome.", "episode": 0, "vintage": ["2012-10-06"], "official_website": [[]], "opening_theme": ["\"Moshimo no Hanashi\" by nano.RIPE", "\"23:40\" by Hyadain feat. Base Ball Bear"], "ending_theme": ["\"\u266aPride on Everyday\uff08\u30d7\u30e9\u30a4\u30c9\u30fb\u30aa\u30f3\u30fb\u30a8\u30d6\u30ea\u30c7\u30a4)\" by Sphere", "\"Yume Sketch\" by JAM Project"], "insert_song": [], "image": "https://cdn.animenewsnetwork.com/thumbnails/fit200x200/encyc/A13867-3342059965.1338079644.jpg", "file_category": "b"}