{"show_name": "Alice or Alice (TV)", "other_title": ["\u0410\u043b\u0438\u0441\u0430 \u0438\u043b\u0438 \u0410\u043b\u0438\u0441\u0430: \u0411\u0440\u0430\u0442-\u0441\u0438\u0441\u043a\u043e\u043d\u0449\u0438\u043a \u0438 \u0441\u0451\u0441\u0442\u0440\u044b-\u0431\u043b\u0438\u0437\u043d\u044f\u0448\u043a\u0438 (Russian)", "\u3042\u308a\u3059or\u3042\u308a\u3059 (Japanese)"], "genre": ["comedy", "slice of life"], "theme": ["ecchi", "family", "fanservice", "imouto", "twins"], "plot": "Twin sisters Rise and Airi live a fun-filled life with their older brother who is slightly attracted to them. (from manga)", "episode": "12", "vintage": ["2018-04-04"], "official_website": "http://alice-or-alice.com/", "opening_theme": ["\"A or A!?\" by petit milady"], "ending_theme": ["\"LONELY ALICE\" by Pyxis"], "insert_song": [], "image": "https://cdn.animenewsnetwork.com/thumbnails/fit200x200/encyc/A19934-2454289477.1513793820.jpg", "file_category": "a"}