{"show_name": "Blue Butterfly Fish (OAV)", "other_title": ["B.B. Fish", "B.B. \u30d5\u30a3\u30c3\u30b7\u30e5 (Japanese)"], "genre": ["drama", "romance", "supernatural"], "theme": [], "plot": "Ushio is a freediver with strange powers. He and his friends are at a tropical land in search of a rare fish, the Blue Butterfly. This pursuit leads them to Ayuuru, a local girl who might know where to find the legendary fish.", "episode": "1", "vintage": ["1994-02-25"], "official_website": [[]], "opening_theme": [], "ending_theme": [], "insert_song": [], "image": "https://cdn.animenewsnetwork.com/thumbnails/fit200x200/encyc/A3282-3127701240.1489748552.jpg", "file_category": "b"}