{"show_name": "Voogie's Angel (OAV)", "other_title": ["Denn\u014d Sentai Voogie's Angel (Japanese)", "\u96fb\u8133\u6226\u968a\u30f4\u30ae\u30a3'\u30ba\u2606\u30a8\u30f3\u30b8\u30a7\u30eb (Japanese)"], "genre": ["science fiction"], "theme": ["alien", "cyborg", "mecha"], "plot": "A hundred years after Earth is invaded by aliens, the last remnants of the human race dwell in underwater \"Aqua Bases.\" A team of five cybernetically enhanced women is trained for the purpose of carrying out guerrilla attacks against the occupying forces. Earth`s last hope for salvation is...Voogie's Angels.", "episode": "3", "vintage": ["1997-10-24 to 1998-07-24"], "official_website": [[]], "opening_theme": ["\"Motto Motto Radical Fight\" by Aya Hisakawa, Kotono Mitsuishi, Kikuko Inoue, Shiho Kikuchi and Sakura Tange"], "ending_theme": ["\"Ganbare! Otokonoko\" by Sakura Tange and Shiho Kikuchi (ep 1)", "\"Namida no 5 Byoumai\" by Sakura Tange (ep 2)", "\"Dreams\" by Aya Hisakawa (ep 3)"], "insert_song": [], "image": "https://cdn.animenewsnetwork.com/thumbnails/fit200x200/encyc/A93-23.jpg", "file_category": "d"}