{"show_name": "El Hazard: The Alternative World (TV)", "other_title": ["El Hazard - Les Mondes Alternatifs (French)", "Ijigen no Sekai El Hazard (Japanese)", "\u7570\u6b21\u5143\u306e\u4e16\u754c\u30a8\u30eb\u30cf\u30b6\u30fc\u30c9 (Japanese)", "\u7570\u6b21\u5143\u4e16\u754c (Chinese (Taiwan))"], "genre": ["adventure", "comedy", "fantasy", "romance"], "theme": ["isekai", "other world"], "plot": "Miz plans to retire as a Great Priestess of Water to married life with her darling Fujisawa and as replacement the young Qawoor Towles arrives to Floristica. Jinnai sees Qawoor's initiation ceremony as a chance to infiltrate Makoto's laboratory but accidentally activates a mysterious thingy that sends them all through the dimensions to a grey industrial city protected by a huge castle in an alternative world.", "episode": "13", "vintage": ["1998-01-08 to 1998-03-25"], "official_website": "http://www.aicanime.com/products/elhazard/index.html", "opening_theme": ["\"13 Gatsu no Shukumei\" by Fence of Defense"], "ending_theme": ["\"Kami-sama ga Kureta Hi\" by Sora Izumikawa (eps 1-12)", "\"Love Mania!\" by Maaya Sakamoto, Rio Natsuki, Etsuko Kozukura, Kyoko Tsuruno (ep 13)"], "insert_song": [], "image": "https://cdn.animenewsnetwork.com/thumbnails/fit200x200/encyc/A598-14.jpg", "file_category": "e"}