{"show_name": "Devilman (TV)", "other_title": ["\u0427\u0435\u043b\u043e\u0432\u0435\u043a-\u0414\u044c\u044f\u0432\u043e\u043b (Russian)", "\u30c7\u30d3\u30eb\u30de\u30f3 (Japanese)"], "genre": ["action", "adventure", "horror", "supernatural"], "theme": [], "plot": "Devilman, one of the soldiers in the Demon clan, is ordered by the greatest demon to spread chaos in the earth. He successfully haunts the body of Akira, an orphan, and goes in his way to attend to his duties. In the mean time, the Demon clan discovers that he has betrayed them. The reason was love. Demon after demon was sent to defy Devilman. All have lost, However, and from here continues the story.", "episode": "39", "vintage": ["1972-07-08 to 1973-04-07"], "official_website": "http://www.toei-anim.co.jp/lineup/tv/devilman/", "opening_theme": ["\"Devilman no Uta (\u30c7\u30d3\u30eb\u30de\u30f3\u306e\u6b4c; Devilman's Song)\" by Keizo Toda"], "ending_theme": ["\"Kyou mo Dokoka de Devilman (\u4eca\u65e5\u3082\u4f55\u51e6\u304b\u3067\u30c7\u30d3\u30eb\u30de\u30f3)\" by Keizo Toda"], "insert_song": [], "image": "https://cdn.animenewsnetwork.com/thumbnails/fit200x200/encyc/A578-3127683524.1546416965.jpg", "file_category": "d"}