{"show_name": "Casshan (TV)", "other_title": ["Kyashan - Il Ragazzo Androide (Italian)", "Shinz\u014d Ningen Casshan (Japanese)", "Superboy Gal\u00e1ctico (Spanish)", "\u65b0\u9020\u4eba\u9593\u30ad\u30e3\u30b7\u30e3\u30fc\u30f3 (Japanese)"], "genre": ["action", "adventure", "science fiction"], "theme": ["android", "mecha"], "plot": "", "episode": "35", "vintage": ["1973-10-02 to 1974-06-25", "2000 (Latin America)"], "official_website": "http://www.tatsunoko.co.jp/works/archive/cassyan.html", "opening_theme": ["\"Tatakae! Casshan\" by Isao Sasaki"], "ending_theme": ["\"Are wa Shinzo Ningen\" by Isao Sasaki"], "insert_song": [], "image": "https://cdn.animenewsnetwork.com/thumbnails/fit200x200/encyc/A2174-17.jpg", "file_category": "c"}